{
"type": "FeatureCollection",

                                                                                                                                  
"features": [
{ "type": "Feature", "properties": { "osm_id": "2169262377", "name": "1", "barrier": null, "highway": null, "ref": null, "address": null, "is_in": null, "place": null, "man_made": null, "other_tags": "\"tourism\"=>\"camp_site\"" }, "geometry": { "type": "Point", "coordinates": [ -71.39177, 42.50224 ] } },
{ "type": "Feature", "properties": { "osm_id": "2169262543", "name": "3", "barrier": null, "highway": null, "ref": null, "address": null, "is_in": null, "place": null, "man_made": null, "other_tags": "\"tourism\"=>\"camp_site\"" }, "geometry": { "type": "Point", "coordinates": [ -71.3926, 42.50309 ] } },
{ "type": "Feature", "properties": { "osm_id": "2169262634", "name": "6", "barrier": null, "highway": null, "ref": null, "address": null, "is_in": null, "place": null, "man_made": null, "other_tags": "\"tourism\"=>\"camp_site\"" }, "geometry": { "type": "Point", "coordinates": [ -71.39628, 42.50339 ] } },
{ "type": "Feature", "properties": { "osm_id": "2169262652", "name": "4", "barrier": null, "highway": null, "ref": null, "address": null, "is_in": null, "place": null, "man_made": null, "other_tags": "\"tourism\"=>\"camp_site\"" }, "geometry": { "type": "Point", "coordinates": [ -71.3941, 42.50347 ] } },
{ "type": "Feature", "properties": { "osm_id": "2169262703", "name": "5", "barrier": null, "highway": null, "ref": null, "address": null, "is_in": null, "place": null, "man_made": null, "other_tags": "\"tourism\"=>\"camp_site\"" }, "geometry": { "type": "Point", "coordinates": [ -71.3948, 42.5038 ] } },
{ "type": "Feature", "properties": { "osm_id": "2169262743", "name": "7", "barrier": null, "highway": null, "ref": null, "address": null, "is_in": null, "place": null, "man_made": null, "other_tags": "\"tourism\"=>\"camp_site\"" }, "geometry": { "type": "Point", "coordinates": [ -71.39755, 42.50406 ] } },
{ "type": "Feature", "properties": { "osm_id": "4584515404", "name": "2", "barrier": null, "highway": null, "ref": null, "address": null, "is_in": null, "place": null, "man_made": null, "other_tags": "\"tourism\"=>\"camp_site\"" }, "geometry": { "type": "Point", "coordinates": [ -71.3922071, 42.5021119 ] } }
]
}
