{
"type": "FeatureCollection",
"crs": { "type": "name", "properties": { "name": "urn:ogc:def:crs:OGC:1.3:CRS84" } },
                                                                                                                                  
"features": [
{ "type": "Feature", "properties": { "osm_id": "2169262377", "address": null, "barrier": null, "highway": null, "is_in": null, "man_made": null, "name": "1", "place": null, "ref": null, "other_tags": "\"tourism\"=>\"camp_site\"" }, "geometry": { "type": "Point", "coordinates": [ -71.39177, 42.50224 ] } },
{ "type": "Feature", "properties": { "osm_id": "2169262543", "address": null, "barrier": null, "highway": null, "is_in": null, "man_made": null, "name": "3", "place": null, "ref": null, "other_tags": "\"tourism\"=>\"camp_site\"" }, "geometry": { "type": "Point", "coordinates": [ -71.3926, 42.50309 ] } },
{ "type": "Feature", "properties": { "osm_id": "2169262634", "address": null, "barrier": null, "highway": null, "is_in": null, "man_made": null, "name": "6", "place": null, "ref": null, "other_tags": "\"tourism\"=>\"camp_site\"" }, "geometry": { "type": "Point", "coordinates": [ -71.39628, 42.50339 ] } },
{ "type": "Feature", "properties": { "osm_id": "2169262652", "address": null, "barrier": null, "highway": null, "is_in": null, "man_made": null, "name": "4", "place": null, "ref": null, "other_tags": "\"tourism\"=>\"camp_site\"" }, "geometry": { "type": "Point", "coordinates": [ -71.3941, 42.50347 ] } },
{ "type": "Feature", "properties": { "osm_id": "2169262703", "address": null, "barrier": null, "highway": null, "is_in": null, "man_made": null, "name": "5", "place": null, "ref": null, "other_tags": "\"tourism\"=>\"camp_site\"" }, "geometry": { "type": "Point", "coordinates": [ -71.3948, 42.5038 ] } },
{ "type": "Feature", "properties": { "osm_id": "2169262743", "address": null, "barrier": null, "highway": null, "is_in": null, "man_made": null, "name": "7", "place": null, "ref": null, "other_tags": "\"tourism\"=>\"camp_site\"" }, "geometry": { "type": "Point", "coordinates": [ -71.39755, 42.50406 ] } },
{ "type": "Feature", "properties": { "osm_id": "4584515404", "address": null, "barrier": null, "highway": null, "is_in": null, "man_made": null, "name": "2", "place": null, "ref": null, "other_tags": "\"tourism\"=>\"camp_site\"" }, "geometry": { "type": "Point", "coordinates": [ -71.3922071, 42.5021119 ] } }
]
}
