{
"type": "FeatureCollection",
"crs": { "type": "name", "properties": { "name": "urn:ogc:def:crs:OGC:1.3:CRS84" } },
                                                                                                                                  
"features": [
{ "type": "Feature", "properties": { "osm_id": "2169262377", "addr_housenumber": null, "addr_street": null, "addr_city": null, "addr_state": null, "addr_postcode": null, "name": "1", "surface": null, "other_tags": "\"tourism\"=>\"camp_site\"" }, "geometry": { "type": "Point", "coordinates": [ -71.39177, 42.50224 ] } },
{ "type": "Feature", "properties": { "osm_id": "2169262543", "addr_housenumber": null, "addr_street": null, "addr_city": null, "addr_state": null, "addr_postcode": null, "name": "3", "surface": null, "other_tags": "\"tourism\"=>\"camp_site\"" }, "geometry": { "type": "Point", "coordinates": [ -71.3926, 42.50309 ] } },
{ "type": "Feature", "properties": { "osm_id": "2169262634", "addr_housenumber": null, "addr_street": null, "addr_city": null, "addr_state": null, "addr_postcode": null, "name": "6", "surface": null, "other_tags": "\"tourism\"=>\"camp_site\"" }, "geometry": { "type": "Point", "coordinates": [ -71.39628, 42.50339 ] } },
{ "type": "Feature", "properties": { "osm_id": "2169262652", "addr_housenumber": null, "addr_street": null, "addr_city": null, "addr_state": null, "addr_postcode": null, "name": "4", "surface": null, "other_tags": "\"tourism\"=>\"camp_site\"" }, "geometry": { "type": "Point", "coordinates": [ -71.3941, 42.50347 ] } },
{ "type": "Feature", "properties": { "osm_id": "2169262703", "addr_housenumber": null, "addr_street": null, "addr_city": null, "addr_state": null, "addr_postcode": null, "name": "5", "surface": null, "other_tags": "\"tourism\"=>\"camp_site\"" }, "geometry": { "type": "Point", "coordinates": [ -71.3948, 42.5038 ] } },
{ "type": "Feature", "properties": { "osm_id": "2169262743", "addr_housenumber": null, "addr_street": null, "addr_city": null, "addr_state": null, "addr_postcode": null, "name": "7", "surface": null, "other_tags": "\"tourism\"=>\"camp_site\"" }, "geometry": { "type": "Point", "coordinates": [ -71.39755, 42.50406 ] } },
{ "type": "Feature", "properties": { "osm_id": "4584515404", "addr_housenumber": null, "addr_street": null, "addr_city": null, "addr_state": null, "addr_postcode": null, "name": "2", "surface": null, "other_tags": "\"tourism\"=>\"camp_site\"" }, "geometry": { "type": "Point", "coordinates": [ -71.3922071, 42.5021119 ] } }
]
}
